LICENSE
MANIFEST.in
README.md
setup.py
phonebox_plugin/__init__.py
phonebox_plugin/admin.py
phonebox_plugin/choices.py
phonebox_plugin/filters.py
phonebox_plugin/forms.py
phonebox_plugin/models.py
phonebox_plugin/navigation.py
phonebox_plugin/tables.py
phonebox_plugin/urls.py
phonebox_plugin/views.py
phonebox_plugin.egg-info/PKG-INFO
phonebox_plugin.egg-info/SOURCES.txt
phonebox_plugin.egg-info/dependency_links.txt
phonebox_plugin.egg-info/top_level.txt
phonebox_plugin/api/__init__.py
phonebox_plugin/api/serializers.py
phonebox_plugin/api/urls.py
phonebox_plugin/api/views.py
phonebox_plugin/migrations/0001_initial.py
phonebox_plugin/migrations/0002_alter_number_id.py
phonebox_plugin/migrations/0003_voicecircuit.py
phonebox_plugin/migrations/0004_alter_number_created_alter_number_id_and_more.py
phonebox_plugin/migrations/__init__.py
phonebox_plugin/templates/phonebox_plugin/add_number.html
phonebox_plugin/templates/phonebox_plugin/add_number_3.x.html
phonebox_plugin/templates/phonebox_plugin/add_voice_circuit.html
phonebox_plugin/templates/phonebox_plugin/add_voice_circuit_3.x.html
phonebox_plugin/templates/phonebox_plugin/list_view.html
phonebox_plugin/templates/phonebox_plugin/list_view_3.4.html
phonebox_plugin/templates/phonebox_plugin/list_view_3.x.html
phonebox_plugin/templates/phonebox_plugin/number.html
phonebox_plugin/templates/phonebox_plugin/number_3.x.html
phonebox_plugin/templates/phonebox_plugin/number_list_view_4.x.html
phonebox_plugin/templates/phonebox_plugin/obj_table.html
phonebox_plugin/templates/phonebox_plugin/tags_panel.html
phonebox_plugin/templates/phonebox_plugin/voice_circuit.html
phonebox_plugin/templates/phonebox_plugin/voice_circuit_3.x.html
phonebox_plugin/templates/phonebox_plugin/voice_circuit_list_view.html
phonebox_plugin/templates/phonebox_plugin/voice_circuit_list_view_3.4.html
phonebox_plugin/templates/phonebox_plugin/voice_circuit_list_view_3.x.html
phonebox_plugin/templates/phonebox_plugin/voice_circuit_list_view_4.x.html