Metadata-Version: 2.1
Name: phonebox-plugin
Version: 0.0.10
Summary: A phone numbers management plugin for NetBox.
Home-page: https://github.com/iDebugAll/phonebox-plugin.git
Download-URL: https://github.com/iDebugAll/phonebox-plugin/archive/v0.0.10.tar.gz
Author: Igor Korotchenkov
Author-email: iDebugAll@gmail.com
License: MIT
Keywords: netbox,netbox-plugin,plugin
Classifier: Development Status :: 4 - Beta
Classifier: Programming Language :: Python :: 3
Classifier: Programming Language :: Python :: 3.6
Classifier: Programming Language :: Python :: 3.7
Classifier: Programming Language :: Python :: 3.8
License-File: LICENSE
